soup_files/__init__.py
soup_files/__main__.py
soup_files/files.py
soup_files/progress.py
soup_files/version.py
soup_files/installer/packages.py
soup_files-1.4.2.dist-info/METADATA
soup_files-1.4.2.dist-info/WHEEL
soup_files-1.4.2.dist-info/top_level.txt
soup_files-1.4.2.dist-info/RECORD
