Metadata-Version: 2.4
Name: soup_files
Version: 1.4.2
Summary: soup_files
Author: Bruno Chaves
Requires-Python: >=3.11
